.gitignore
MANIFEST.in
README.rst
setup.py
tox.ini
images/coloured_argparse.png
images/coloured_logging.png
supercli/LICENSE.txt
supercli/TODO.rst
supercli/VERSION_HIST.rst
supercli/__init__.py
supercli/argparse.py
supercli/autocomplete.py
supercli/excepttools.py
supercli/logging.py
supercli.egg-info/PKG-INFO
supercli.egg-info/SOURCES.txt
supercli.egg-info/dependency_links.txt
supercli.egg-info/not-zip-safe
supercli.egg-info/requires.txt
supercli.egg-info/top_level.txt
supercli/examples/_coloured_completer
supercli/examples/coloured_completer.py
supercli/examples/standalone_logger.py
supercli/tests/test_supercli/test_logging.py