Metadata-Version: 1.1
Name: supercli
Version: 0.0a5
Summary: Toolkit to quickly create readable, user-friendly CLI interfaces with automatic shell-autocompletion
Home-page: https://github.com/willjp/supercli
Author: Will Pittman
Author-email: willjpittman@gmail.com
License: BSD
Keywords: supercli cli color colour argparse logging interface
Platform: UNKNOWN
Classifier: Development Status :: 3 - Alpha
Classifier: License :: OSI Approved :: BSD License
Classifier: Programming Language :: Python
Classifier: Programming Language :: Python :: 2.7
Classifier: Programming Language :: Python :: 3
Classifier: Operating System :: Microsoft :: Windows
Classifier: Operating System :: POSIX :: Linux
Classifier: Operating System :: POSIX :: BSD
